training_pipeline/.DS_Store
training_pipeline/__init__.py
training_pipeline/best_config.py
training_pipeline/configs/__init__.py
training_pipeline/configs/gridsearch.py
training_pipeline/data.py
training_pipeline/hyperparameter_tuning.py
training_pipeline/models.py
training_pipeline/settings.py
training_pipeline/train.py
training_pipeline/transformers.py
training_pipeline/utils.py
cat_spend_training_pipeline-0.1.1.dist-info/METADATA
cat_spend_training_pipeline-0.1.1.dist-info/WHEEL
cat_spend_training_pipeline-0.1.1.dist-info/RECORD
