Metadata-Version: 2.1
Name: cat-spend-training-pipeline
Version: 0.1.1
Summary: 
Author: danilog
Requires-Python: >=3.9,<3.10
Classifier: Programming Language :: Python :: 3
Classifier: Programming Language :: Python :: 3.9
Requires-Dist: Jinja2 (==3.0.1)
Requires-Dist: fire (>=0.5.0,<0.6.0)
Requires-Dist: hopsworks (==3.4.3)
Requires-Dist: lightgbm (>=4.2.0,<5.0.0)
Requires-Dist: matplotlib (>=3.8.2,<4.0.0)
Requires-Dist: pyarrow (>=11.0.0,<12.0.0)
Requires-Dist: python-dotenv (>=1.0.0,<2.0.0)
Requires-Dist: seaborn (>=0.13.1,<0.14.0)
Requires-Dist: sktime (>=0.25.0,<0.26.0)
Requires-Dist: wandb (>=0.16.1,<0.17.0)
